superiq/__init__.py
superiq/basalforebrain.py
superiq/basalforebrainOR.py
superiq/basalforebrain_seg.py
superiq/collect_volume_files.py
superiq/deep_dkt.py
superiq/deep_hippo.py
superiq/pipeline_utils.py
superiq/segmentation_validation.py
superiq/super_resolution_segmentation_per_label.py
superiq/super_resolution_segmentation_with_probabilities.py
superiq-0.0.2.dist-info/LICENSE
superiq-0.0.2.dist-info/METADATA
superiq-0.0.2.dist-info/WHEEL
superiq-0.0.2.dist-info/top_level.txt
superiq-0.0.2.dist-info/RECORD
