Metadata-Version: 2.1
Name: superiq
Version: 0.0.2
Summary: Super-resolution image quantification
Home-page: https://github.com/stnava/superiq
Author: Avants and Gosselin
Author-email: stnava@gmail.com
License: Apache 2.0
Platform: UNKNOWN
License-File: LICENSE
